{
    "ばくおんライオン": "ばくおんライオン",
    "ターン開始時○〆好調状態の場合、パラメータ<nobr>+6</nobr>\n（レッスン内1回）": "ターン開始時○〆好調状態の場合、パラメータ<nobr>+6</nobr>\n（レッスン内1回）",
    "ばくおんライオン+": "ばくおんライオン+",
    "ターン開始時○〆好調状態の場合、パラメータ<nobr>+11</nobr>\n（レッスン内1回）": "ターン開始時○〆好調状態の場合、パラメータ<nobr>+11</nobr>\n（レッスン内1回）",
    "必携ステンレスボトル": "必携ステンレスボトル",
    "ターン開始時○〆集中が3以上の場合、○〆集中<nobr>+4</nobr>\n（レッスン内1回）": "ターン開始時○〆集中が3以上の場合、○〆集中<nobr>+4</nobr>\n（レッスン内1回）",
    "必携ステンレスボトル+": "必携ステンレスボトル+",
    "ターン開始時○〆集中が3以上の場合、○〆集中<nobr>+6</nobr>\n（レッスン内1回）": "ターン開始時○〆集中が3以上の場合、○〆集中<nobr>+6</nobr>\n（レッスン内1回）",
    "紳士風ハンカチーフ": "紳士風ハンカチーフ",
    "ターン開始時○〆好調状態の場合、○〆集中<nobr>+1</nobr>\n（レッスン内2回）": "ターン開始時○〆好調状態の場合、○〆集中<nobr>+1</nobr>\n（レッスン内2回）",
    "紳士風ハンカチーフ+": "紳士風ハンカチーフ+",
    "ターン開始時○〆好調状態の場合、○〆集中<nobr>+2</nobr>\n（レッスン内2回）": "ターン開始時○〆好調状態の場合、○〆集中<nobr>+2</nobr>\n（レッスン内2回）",
    "いつものメイクポーチ": "いつものメイクポーチ",
    "○〆アクティブスキルカード使用時体力が50%以上の場合、○〆集中<nobr>+2</nobr>\n（レッスン内1回）": "○〆アクティブスキルカード使用時体力が50%以上の場合、○〆集中<nobr>+2</nobr>\n（レッスン内1回）",
    "いつものメイクポーチ+": "いつものメイクポーチ+",
    "○〆アクティブスキルカード使用時体力が50%以上の場合、○〆集中<nobr>+3</nobr>\n（レッスン内1回）": "○〆アクティブスキルカード使用時体力が50%以上の場合、○〆集中<nobr>+3</nobr>\n（レッスン内1回）",
    "ピンクのお揃いブレス": "ピンクのお揃いブレス",
    "ターン開始時、○〆集中<nobr>+1</nobr>\n（レッスン内2回）": "ターン開始時、○〆集中<nobr>+1</nobr>\n（レッスン内2回）",
    "ピンクのお揃いブレス+": "ピンクのお揃いブレス+",
    "ターン開始時、○〆集中<nobr>+1</nobr>\n（レッスン内3回）": "ターン開始時、○〆集中<nobr>+1</nobr>\n（レッスン内3回）",
    "ちびども手作りメダル": "ちびども手作りメダル",
    "ターン終了時○〆好印象が6以上の場合、○〆好印象<nobr>+2</nobr>\n（レッスン内2回）": "ターン終了時○〆好印象が6以上の場合、○〆好印象<nobr>+2</nobr>\n（レッスン内2回）",
    "ちびども手作りメダル+": "ちびども手作りメダル+",
    "ターン終了時○〆好印象が6以上の場合、○〆好印象<nobr>+2</nobr>\n（レッスン内3回）": "ターン終了時○〆好印象が6以上の場合、○〆好印象<nobr>+2</nobr>\n（レッスン内3回）",
    "超絶あんみんマスク": "超絶あんみんマスク",
    "ターン開始時最終ターンの場合、○〆元気の<nobr>50%</nobr>分パラメータ上昇\n○〆体力消費<nobr>1</nobr>": "ターン開始時最終ターンの場合、○〆元気の<nobr>50%</nobr>分パラメータ上昇\n○〆体力消費<nobr>1</nobr>",
    "超絶あんみんマスク+": "超絶あんみんマスク+",
    "ターン開始時最終ターンの場合、○〆元気の<nobr>70%</nobr>分パラメータ上昇\n○〆体力消費<nobr>1</nobr>": "ターン開始時最終ターンの場合、○〆元気の<nobr>70%</nobr>分パラメータ上昇\n○〆体力消費<nobr>1</nobr>",
    "緑のお揃いブレス": "緑のお揃いブレス",
    "○〆好印象が増加後、○〆好印象<nobr>+3</nobr>\n（レッスン内1回）": "○〆好印象が増加後、○〆好印象<nobr>+3</nobr>\n（レッスン内1回）",
    "緑のお揃いブレス+": "緑のお揃いブレス+",
    "○〆好印象が増加後、○〆好印象<nobr>+5</nobr>\n（レッスン内1回）": "○〆好印象が増加後、○〆好印象<nobr>+5</nobr>\n（レッスン内1回）",
    "願いを叶えるお守り": "願いを叶えるお守り",
    "○〆やる気が増加後、○〆やる気<nobr>+2</nobr>\n（レッスン内1回）": "○〆やる気が増加後、○〆やる気<nobr>+2</nobr>\n（レッスン内1回）",
    "願いを叶えるお守り+": "願いを叶えるお守り+",
    "○〆やる気が増加後、○〆やる気<nobr>+3</nobr>\n（レッスン内1回）": "○〆やる気が増加後、○〆やる気<nobr>+3</nobr>\n（レッスン内1回）",
    "テクノドッグ": "テクノドッグ",
    "スキルカード使用後○〆やる気が3以上の場合、○〆やる気<nobr>+2</nobr>\n（レッスン内1回）": "スキルカード使用後○〆やる気が3以上の場合、○〆やる気<nobr>+2</nobr>\n（レッスン内1回）",
    "テクノドッグ+": "テクノドッグ+",
    "スキルカード使用後○〆やる気が3以上の場合、○〆やる気<nobr>+3</nobr>\n（レッスン内1回）": "スキルカード使用後○〆やる気が3以上の場合、○〆やる気<nobr>+3</nobr>\n（レッスン内1回）",
    "咲季の完全食レシピ": "咲季の完全食レシピ",
    "ターン開始時○〆好調状態の場合、○〆元気<nobr>+9</nobr>\n（レッスン内1回）": "ターン開始時○〆好調状態の場合、○〆元気<nobr>+9</nobr>\n（レッスン内1回）",
    "咲季の完全食レシピ+": "咲季の完全食レシピ+",
    "ターン開始時○〆好調状態の場合、○〆元気<nobr>+12</nobr>\n（レッスン内1回）": "ターン開始時○〆好調状態の場合、○〆元気<nobr>+12</nobr>\n（レッスン内1回）",
    "私の「初」の楽譜": "私の「初」の楽譜",
    "ターン開始時○〆元気が0の場合、体力減少<nobr>1</nobr>\n○〆集中<nobr>+3</nobr>\n（レッスン内2回）": "ターン開始時○〆元気が0の場合、体力減少<nobr>1</nobr>\n○〆集中<nobr>+3</nobr>\n（レッスン内2回）",
    "私の「初」の楽譜+": "私の「初」の楽譜+",
    "ターン開始時○〆元気が0の場合、体力減少<nobr>1</nobr>\n○〆集中<nobr>+4</nobr>\n（レッスン内2回）": "ターン開始時○〆元気が0の場合、体力減少<nobr>1</nobr>\n○〆集中<nobr>+4</nobr>\n（レッスン内2回）",
    "Dearリトルプリンス": "Dearリトルプリンス",
    "○〆好調の効果ターンが増加後、○〆好調<nobr>3ターン</nobr>\n（レッスン内1回）": "○〆好調の効果ターンが増加後、○〆好調<nobr>3ターン</nobr>\n（レッスン内1回）",
    "Dearリトルプリンス+": "Dearリトルプリンス+",
    "○〆好調の効果ターンが増加後、○〆好調<nobr>4ターン</nobr>\n（レッスン内1回）": "○〆好調の効果ターンが増加後、○〆好調<nobr>4ターン</nobr>\n（レッスン内1回）",
    "きみへの差し入れ": "きみへの差し入れ",
    "ターン開始時○〆集中が5以上の場合、体力回復<nobr>2</nobr>\n（レッスン内3回）": "ターン開始時○〆集中が5以上の場合、体力回復<nobr>2</nobr>\n（レッスン内3回）",
    "きみへの差し入れ+": "きみへの差し入れ+",
    "ターン開始時○〆集中が5以上の場合、体力回復<nobr>2</nobr>\n（レッスン内4回）": "ターン開始時○〆集中が5以上の場合、体力回復<nobr>2</nobr>\n（レッスン内4回）",
    "放課後のらくがき": "放課後のらくがき",
    "○〆集中が増加後体力が50%以上の場合、○〆集中<nobr>+2</nobr>\n（レッスン内2回）": "○〆集中が増加後体力が50%以上の場合、○〆集中<nobr>+2</nobr>\n（レッスン内2回）",
    "放課後のらくがき+": "放課後のらくがき+",
    "○〆集中が増加後、○〆集中<nobr>+2</nobr>\n（レッスン内2回）": "○〆集中が増加後、○〆集中<nobr>+2</nobr>\n（レッスン内2回）",
    "お気にのスニーカー": "お気にのスニーカー",
    "ターン終了時○〆元気が7以上の場合、○〆好印象<nobr>+4</nobr>\n（レッスン内1回）": "ターン終了時○〆元気が7以上の場合、○〆好印象<nobr>+4</nobr>\n（レッスン内1回）",
    "お気にのスニーカー+": "お気にのスニーカー+",
    "ターン終了時○〆元気が7以上の場合、○〆好印象<nobr>+5</nobr>\n（レッスン内1回）": "ターン終了時○〆元気が7以上の場合、○〆好印象<nobr>+5</nobr>\n（レッスン内1回）",
    "だれでもわかる入門書": "だれでもわかる入門書",
    "ターン開始時○〆元気が7以上の場合、○〆やる気<nobr>+5</nobr>\n（レッスン内1回）": "ターン開始時○〆元気が7以上の場合、○〆やる気<nobr>+5</nobr>\n（レッスン内1回）",
    "だれでもわかる入門書+": "だれでもわかる入門書+",
    "ターン開始時○〆元気が7以上の場合、○〆やる気<nobr>+6</nobr>\n（レッスン内1回）": "ターン開始時○〆元気が7以上の場合、○〆やる気<nobr>+6</nobr>\n（レッスン内1回）",
    "思い出ロボ": "思い出ロボ",
    "ターン終了時体力が50%以上の場合、○〆好印象<nobr>+3</nobr>\n（レッスン内1回）": "ターン終了時体力が50%以上の場合、○〆好印象<nobr>+3</nobr>\n（レッスン内1回）",
    "思い出ロボ+": "思い出ロボ+",
    "ターン終了時体力が50%以上の場合、○〆好印象<nobr>+4</nobr>\n（レッスン内1回）": "ターン終了時体力が50%以上の場合、○〆好印象<nobr>+4</nobr>\n（レッスン内1回）",
    "しょげないハンカチ": "しょげないハンカチ",
    "○〆アクティブスキルカード使用後、○〆元気の<nobr>60%</nobr>分パラメータ上昇\n○〆体力消費<nobr>2</nobr>\n（レッスン内2回）": "○〆アクティブスキルカード使用後、○〆元気の<nobr>60%</nobr>分パラメータ上昇\n○〆体力消費<nobr>2</nobr>\n（レッスン内2回）",
    "しょげないハンカチ+": "しょげないハンカチ+",
    "○〆アクティブスキルカード使用後、○〆元気の<nobr>70%</nobr>分パラメータ上昇\n○〆体力消費<nobr>2</nobr>\n（レッスン内2回）": "○〆アクティブスキルカード使用後、○〆元気の<nobr>70%</nobr>分パラメータ上昇\n○〆体力消費<nobr>2</nobr>\n（レッスン内2回）",
    "柴犬ポシェット": "柴犬ポシェット",
    "2ターンごとに、○〆元気<nobr>+5</nobr>\n（レッスン内2回）": "2ターンごとに、○〆元気<nobr>+5</nobr>\n（レッスン内2回）",
    "柴犬ポシェット+": "柴犬ポシェット+",
    "2ターンごとに、○〆元気<nobr>+5</nobr>\n（レッスン内3回）": "2ターンごとに、○〆元気<nobr>+5</nobr>\n（レッスン内3回）",
    "美鈴からの贈り物": "美鈴からの贈り物",
    "ボーカルSPレッスン終了時ボーカルが400以上の場合、ランダムなスキルカードを<color=#8581FF>強化</color>": "ボーカルSPレッスン終了時ボーカルが400以上の場合、ランダムなスキルカードを<color=#8581FF>強化</color>",
    "打倒！墾田永年私財法": "打倒！墾田永年私財法",
    "追い込みレッスン終了時ボーカルが400以上の場合、ボーカル上昇+26": "追い込みレッスン終了時ボーカルが400以上の場合、ボーカル上昇+26",
    "手作りのご褒美": "手作りのご褒美",
    "追い込みレッスン終了時ビジュアルが400以上の場合、ビジュアル上昇+26": "追い込みレッスン終了時ビジュアルが400以上の場合、ビジュアル上昇+26",
    "ふわふわでもこもこ": "ふわふわでもこもこ",
    "ダンスSPレッスン終了時、ランダムにPドリンクを2つ獲得": "ダンスSPレッスン終了時、ランダムにPドリンクを2つ獲得",
    "お姉さま大百科": "お姉さま大百科",
    "追い込みレッスン終了時ダンスが400以上の場合、ダンス上昇+26": "追い込みレッスン終了時ダンスが400以上の場合、ダンス上昇+26",
    "例のSSDの秘密": "例のSSDの秘密",
    "ダンスレッスン終了時体力が50%以上の場合、ダンス上昇+13": "ダンスレッスン終了時体力が50%以上の場合、ダンス上昇+13",
    "一緒にお昼寝ポプリ": "一緒にお昼寝ポプリ",
    "ボーカルレッスン終了時体力が50%以上の場合、ボーカル上昇+13": "ボーカルレッスン終了時体力が50%以上の場合、ボーカル上昇+13",
    "私が見つけた逸材メモ": "私が見つけた逸材メモ",
    "ビジュアルレッスン終了時体力が50%以上の場合、ビジュアル上昇+13": "ビジュアルレッスン終了時体力が50%以上の場合、ビジュアル上昇+13",
    "朝一の助け舟": "朝一の助け舟",
    "スキルカード強化時ボーカルが400以上の場合、Pポイント+15": "スキルカード強化時ボーカルが400以上の場合、Pポイント+15",
    "誓いの花びら": "誓いの花びら",
    "ビジュアルSPレッスン終了時ビジュアルが400以上の場合、ランダムなスキルカードを<color=#8581FF>強化</color>": "ビジュアルSPレッスン終了時ビジュアルが400以上の場合、ランダムなスキルカードを<color=#8581FF>強化</color>",
    "はつぼしブローチ": "はつぼしブローチ",
    "レッスン終了時、レッスン報酬のスキルカードの選択肢を追加": "レッスン終了時、レッスン報酬のスキルカードの選択肢を追加",
    "はつぼしブレスレット": "はつぼしブレスレット",
    "SPレッスン終了時、体力消費3\nスキルカードを選択して<color=#8581FF>強化</color>": "SPレッスン終了時、体力消費3\nスキルカードを選択して<color=#8581FF>強化</color>",
    "はつぼし手帳": "はつぼし手帳",
    "ターン開始時○〆集中が5以上の場合、○〆スキルカード使用数追加<nobr>+1</nobr>\n○〆集中<nobr>+2</nobr>\n（レッスン内1回）": "ターン開始時○〆集中が5以上の場合、○〆スキルカード使用数追加<nobr>+1</nobr>\n○〆集中<nobr>+2</nobr>\n（レッスン内1回）",
    "はつぼしTシャツ": "はつぼしTシャツ",
    "ターン開始時○〆好調状態の場合、○〆スキルカード使用数追加<nobr>+1</nobr>\n○〆好調<nobr>2ターン</nobr>\n（レッスン内1回）": "ターン開始時○〆好調状態の場合、○〆スキルカード使用数追加<nobr>+1</nobr>\n○〆好調<nobr>2ターン</nobr>\n（レッスン内1回）",
    "はつぼしキーホルダー": "はつぼしキーホルダー",
    "ターン開始時○〆好印象が3以上の場合、○〆スキルカード使用数追加<nobr>+1</nobr>\n○〆好印象<nobr>+3</nobr>\n（レッスン内1回）": "ターン開始時○〆好印象が3以上の場合、○〆スキルカード使用数追加<nobr>+1</nobr>\n○〆好印象<nobr>+3</nobr>\n（レッスン内1回）",
    "マスコット（非公認）": "マスコット（非公認）",
    "ターン開始時○〆やる気が5以上の場合、○〆スキルカード使用数追加<nobr>+1</nobr>\n○〆やる気<nobr>+3</nobr>\n（レッスン内1回）": "ターン開始時○〆やる気が5以上の場合、○〆スキルカード使用数追加<nobr>+1</nobr>\n○〆やる気<nobr>+3</nobr>\n（レッスン内1回）",
    "共に戦うタオル": "共に戦うタオル",
    "○〆アクティブスキルカード使用後、○〆好調<nobr>1ターン</nobr>\n○〆スキルカード使用数追加<nobr>+1</nobr>\n（レッスン内1回）": "○〆アクティブスキルカード使用後、○〆好調<nobr>1ターン</nobr>\n○〆スキルカード使用数追加<nobr>+1</nobr>\n（レッスン内1回）",
    "共に戦うタオル+": "共に戦うタオル+",
    "○〆アクティブスキルカード使用後、○〆好調<nobr>1ターン</nobr>\n○〆スキルカード使用数追加<nobr>+1</nobr>\n○〆元気<nobr>+5</nobr>\n（レッスン内1回）": "○〆アクティブスキルカード使用後、○〆好調<nobr>1ターン</nobr>\n○〆スキルカード使用数追加<nobr>+1</nobr>\n○〆元気<nobr>+5</nobr>\n（レッスン内1回）",
    "自分を守るイヤホン": "自分を守るイヤホン",
    "スキルカード使用時○〆集中が5以上の場合、○〆スキルカード使用数追加<nobr>+1</nobr>\n○〆集中<nobr>+1</nobr>\n（レッスン内1回）": "スキルカード使用時○〆集中が5以上の場合、○〆スキルカード使用数追加<nobr>+1</nobr>\n○〆集中<nobr>+1</nobr>\n（レッスン内1回）",
    "自分を守るイヤホン+": "自分を守るイヤホン+",
    "スキルカード使用時○〆集中が5以上の場合、○〆スキルカード使用数追加<nobr>+1</nobr>\n○〆集中<nobr>+3</nobr>\n（レッスン内1回）": "スキルカード使用時○〆集中が5以上の場合、○〆スキルカード使用数追加<nobr>+1</nobr>\n○〆集中<nobr>+3</nobr>\n（レッスン内1回）",
    "内なる光の耳飾り": "内なる光の耳飾り",
    "ターン開始時○〆好調状態の場合、○〆集中<nobr>+2</nobr>\n○〆元気<nobr>+1</nobr>\n（レッスン内2回）": "ターン開始時○〆好調状態の場合、○〆集中<nobr>+2</nobr>\n○〆元気<nobr>+1</nobr>\n（レッスン内2回）",
    "内なる光の耳飾り+": "内なる光の耳飾り+",
    "ターン開始時○〆好調状態の場合、○〆集中<nobr>+3</nobr>\n○〆元気<nobr>+1</nobr>\n（レッスン内2回）": "ターン開始時○〆好調状態の場合、○〆集中<nobr>+3</nobr>\n○〆元気<nobr>+1</nobr>\n（レッスン内2回）",
    "等身大のレディリップ": "等身大のレディリップ",
    "ターン開始時残り2ターン以内の場合、パラメータ<nobr>+5</nobr>\n（レッスン内2回）": "ターン開始時残り2ターン以内の場合、パラメータ<nobr>+5</nobr>\n（レッスン内2回）",
    "等身大のレディリップ+": "等身大のレディリップ+",
    "ターン開始時残り3ターン以内の場合、パラメータ<nobr>+5</nobr>\n（レッスン内3回）": "ターン開始時残り3ターン以内の場合、パラメータ<nobr>+5</nobr>\n（レッスン内3回）",
    "ゲーセンの戦利品": "ゲーセンの戦利品",
    "レッスン開始時、○〆集中<nobr>+3</nobr>\n（レッスン内1回）": "レッスン開始時、○〆集中<nobr>+3</nobr>\n（レッスン内1回）",
    "ゲーセンの戦利品+": "ゲーセンの戦利品+",
    "レッスン開始時、○〆集中<nobr>+4</nobr>\n（レッスン内1回）": "レッスン開始時、○〆集中<nobr>+4</nobr>\n（レッスン内1回）",
    "ピッグドリーム貯金箱": "ピッグドリーム貯金箱",
    "スキルカード使用後○〆好印象が6以上の場合、○〆好印象<nobr>+3</nobr>\n○〆スキルカード使用数追加<nobr>+1</nobr>\n（レッスン内1回）": "スキルカード使用後○〆好印象が6以上の場合、○〆好印象<nobr>+3</nobr>\n○〆スキルカード使用数追加<nobr>+1</nobr>\n（レッスン内1回）",
    "ピッグドリーム貯金箱+": "ピッグドリーム貯金箱+",
    "スキルカード使用後○〆好印象が6以上の場合、○〆好印象<nobr>+5</nobr>\n○〆スキルカード使用数追加<nobr>+1</nobr>\n（レッスン内1回）": "スキルカード使用後○〆好印象が6以上の場合、○〆好印象<nobr>+5</nobr>\n○〆スキルカード使用数追加<nobr>+1</nobr>\n（レッスン内1回）",
    "みちくさ研究ノート": "みちくさ研究ノート",
    "ターン開始時残り2ターン以内の場合、○〆元気の<nobr>50%</nobr>分パラメータ上昇\n○〆体力消費<nobr>1</nobr>": "ターン開始時残り2ターン以内の場合、○〆元気の<nobr>50%</nobr>分パラメータ上昇\n○〆体力消費<nobr>1</nobr>",
    "みちくさ研究ノート+": "みちくさ研究ノート+",
    "ターン開始時残り2ターン以内の場合、○〆元気の<nobr>65%</nobr>分パラメータ上昇\n○〆体力消費<nobr>1</nobr>": "ターン開始時残り2ターン以内の場合、○〆元気の<nobr>65%</nobr>分パラメータ上昇\n○〆体力消費<nobr>1</nobr>",
    "夢へのライフログ": "夢へのライフログ",
    "ターン終了時○〆元気が7以上の場合、○〆好印象<nobr>1.5倍</nobr>\n○〆好印象の<nobr>30%</nobr>分パラメータ上昇\n（レッスン内1回）": "ターン終了時○〆元気が7以上の場合、○〆好印象<nobr>1.5倍</nobr>\n○〆好印象の<nobr>30%</nobr>分パラメータ上昇\n（レッスン内1回）",
    "夢へのライフログ+": "夢へのライフログ+",
    "ターン終了時○〆元気が7以上の場合、○〆好印象<nobr>1.5倍</nobr>\n○〆好印象の<nobr>100%</nobr>分パラメータ上昇\n（レッスン内1回）": "ターン終了時○〆元気が7以上の場合、○〆好印象<nobr>1.5倍</nobr>\n○〆好印象の<nobr>100%</nobr>分パラメータ上昇\n（レッスン内1回）",
    "ひみつ特訓カーデ": "ひみつ特訓カーデ",
    "○〆やる気が増加後、○〆やる気<nobr>+3</nobr>\n（レッスン内2回）": "○〆やる気が増加後、○〆やる気<nobr>+3</nobr>\n（レッスン内2回）",
    "ひみつ特訓カーデ+": "ひみつ特訓カーデ+",
    "○〆やる気が増加後、○〆やる気<nobr>+3</nobr>\n（レッスン内3回）": "○〆やる気が増加後、○〆やる気<nobr>+3</nobr>\n（レッスン内3回）",
    "これが、私": "これが、私",
    "ターン終了時○〆好印象が10以上の場合、○〆好印象の<nobr>100%</nobr>分パラメータ上昇\n○〆元気<nobr>+3</nobr>\n（レッスン内2回）": "ターン終了時○〆好印象が10以上の場合、○〆好印象の<nobr>100%</nobr>分パラメータ上昇\n○〆元気<nobr>+3</nobr>\n（レッスン内2回）",
    "これが、私+": "これが、私+",
    "ターン終了時○〆好印象が10以上の場合、○〆好印象の<nobr>100%</nobr>分パラメータ上昇\n○〆元気<nobr>+3</nobr>\n（レッスン内3回）": "ターン終了時○〆好印象が10以上の場合、○〆好印象の<nobr>100%</nobr>分パラメータ上昇\n○〆元気<nobr>+3</nobr>\n（レッスン内3回）",
    "転がり続ける元気の源": "転がり続ける元気の源",
    "○〆メンタルスキルカード使用後○〆やる気が5以上の場合、○〆やる気<nobr>+3</nobr>\n○〆スキルカード使用数追加<nobr>+1</nobr>\n（レッスン内1回）": "○〆メンタルスキルカード使用後○〆やる気が5以上の場合、○〆やる気<nobr>+3</nobr>\n○〆スキルカード使用数追加<nobr>+1</nobr>\n（レッスン内1回）",
    "転がり続ける元気の源+": "転がり続ける元気の源+",
    "○〆メンタルスキルカード使用後○〆やる気が5以上の場合、○〆やる気<nobr>+5</nobr>\n○〆スキルカード使用数追加<nobr>+1</nobr>\n（レッスン内1回）": "○〆メンタルスキルカード使用後○〆やる気が5以上の場合、○〆やる気<nobr>+5</nobr>\n○〆スキルカード使用数追加<nobr>+1</nobr>\n（レッスン内1回）",
    "得体のしれないモノ": "得体のしれないモノ",
    "【ビジュアルレッスン・ビジュアルターンのみ】ターン開始時、○〆パラメータ上昇量増加<nobr>50%</nobr>（<nobr>1ターン</nobr>）\n（レッスン内3回）": "【ビジュアルレッスン・ビジュアルターンのみ】ターン開始時、○〆パラメータ上昇量増加<nobr>50%</nobr>（<nobr>1ターン</nobr>）\n（レッスン内3回）",
    "星のリトルプリンス": "星のリトルプリンス",
    "【ビジュアルレッスン・ビジュアルターンのみ】ターン開始時、○〆固定元気<nobr>+2</nobr>": "【ビジュアルレッスン・ビジュアルターンのみ】ターン開始時、○〆固定元気<nobr>+2</nobr>",
    "悔しさの象徴": "悔しさの象徴",
    "【ダンスレッスン・ダンスターンのみ】ターン開始時、○〆パラメータ上昇量増加<nobr>50%</nobr>（<nobr>1ターン</nobr>）\n（レッスン内3回）": "【ダンスレッスン・ダンスターンのみ】ターン開始時、○〆パラメータ上昇量増加<nobr>50%</nobr>（<nobr>1ターン</nobr>）\n（レッスン内3回）",
    "曇りをぬぐったタオル": "曇りをぬぐったタオル",
    "【ボーカルレッスン・ボーカルターンのみ】○〆アクティブスキルカード使用時、体力回復<nobr>2</nobr>\n（レッスン内3回）": "【ボーカルレッスン・ボーカルターンのみ】○〆アクティブスキルカード使用時、体力回復<nobr>2</nobr>\n（レッスン内3回）",
    "スカウト遮り帽": "スカウト遮り帽",
    "【ボーカルレッスン・ボーカルターンのみ】ターン開始時、スキルカードを引く\n○〆固定元気<nobr>+2</nobr>\n（レッスン内3回）": "【ボーカルレッスン・ボーカルターンのみ】ターン開始時、スキルカードを引く\n○〆固定元気<nobr>+2</nobr>\n（レッスン内3回）",
    "信頼の証": "信頼の証",
    "お出かけ終了時、体力回復9": "お出かけ終了時、体力回復9",
    "満開ペアヘアピン": "満開ペアヘアピン",
    "【ビジュアルレッスン・ビジュアルターンのみ】○〆アクティブスキルカード使用時、体力回復<nobr>2</nobr>\n（レッスン内3回）": "【ビジュアルレッスン・ビジュアルターンのみ】○〆アクティブスキルカード使用時、体力回復<nobr>2</nobr>\n（レッスン内3回）",
    "仲直りのきっかけ": "仲直りのきっかけ",
    "【ビジュアルレッスン・ビジュアルターンのみ】ターン開始時、○〆スキルカード使用数追加<nobr>+1</nobr>\n（レッスン内1回）": "【ビジュアルレッスン・ビジュアルターンのみ】ターン開始時、○〆スキルカード使用数追加<nobr>+1</nobr>\n（レッスン内1回）",
    "夢にあふれた大荷物": "夢にあふれた大荷物",
    "【ダンスレッスン・ダンスターンのみ】ターン開始時、○〆スキルカード使用数追加<nobr>+1</nobr>\n（レッスン内1回）": "【ダンスレッスン・ダンスターンのみ】ターン開始時、○〆スキルカード使用数追加<nobr>+1</nobr>\n（レッスン内1回）",
    "天川ラーメン巡り": "天川ラーメン巡り",
    "【ボーカルレッスン・ボーカルターンのみ】ターン開始時、○〆スキルカード使用数追加<nobr>+1</nobr>\n（レッスン内1回）": "【ボーカルレッスン・ボーカルターンのみ】ターン開始時、○〆スキルカード使用数追加<nobr>+1</nobr>\n（レッスン内1回）"
}